bob/__init__.py
bob/extension/__init__.py
bob/extension/config.py
bob/extension/download.py
bob/extension/log.py
bob/extension/rc_config.py
bob/extension/test_click_helper.py
bob/extension/test_config.py
bob/extension/test_download.py
bob/extension/test_rc.py
bob/extension/test_utils.py
bob/extension/utils.py
bob/extension/data/__init__.py
bob/extension/data/basic_config.py
bob/extension/data/config_with_module.py
bob/extension/data/defaults-config
bob/extension/data/example_csv_filelist.tar.gz
bob/extension/data/load_config.py
bob/extension/data/resource_config.py
bob/extension/data/resource_config2.py
bob/extension/data/test_dump_config.py
bob/extension/data/test_dump_config2.py
bob/extension/data/test_list_folders1.tar.gz
bob/extension/data/test_list_folders2.tar.gz
bob/extension/data/verbose_config.py
bob/extension/data/subpackage/__init__.py
bob/extension/data/subpackage/config.py
bob/extension/data/test_list_folders/README.rst
bob/extension/data/test_list_folders/database1/README1.rst
bob/extension/data/test_list_folders/database1/protocol1/dev.csv
bob/extension/data/test_list_folders/database1/protocol1/train.csv
bob/extension/data/test_list_folders/database1/protocol2/dev.csv
bob/extension/data/test_list_folders/database1/protocol2/eval.csv
bob/extension/data/test_list_folders/database2/README2.rst
bob/extension/data/test_list_folders/database2/protocol2/dev.csv
bob/extension/data/test_list_folders/database2/protocol2/eval.csv
bob/extension/data/test_list_folders/database2/protocol3/dev.csv
bob/extension/data/test_list_folders/database2/protocol3/train.csv
bob/extension/scripts/__init__.py
bob/extension/scripts/click_helper.py
bob/extension/scripts/config.py
bob/extension/scripts/main_cli.py
bob.extension-7.0.5.dist-info/LICENSE
bob.extension-7.0.5.dist-info/METADATA
bob.extension-7.0.5.dist-info/WHEEL
bob.extension-7.0.5.dist-info/entry_points.txt
bob.extension-7.0.5.dist-info/top_level.txt
bob.extension-7.0.5.dist-info/RECORD
