Metadata-Version: 2.1
Name: bob.extension
Version: 7.0.5
Summary: Building of Python/C++ extensions for Bob
Home-page: http://gitlab.idiap.ch/bob/bob.extension
Author: Andre Anjos
Author-email: andre.anjos@idiap.ch
License: BSD
Project-URL: Documentation, https://www.idiap.ch/software/bob/docs/bob/bob.extension/master/
Classifier: Framework :: Bob
Classifier: Development Status :: 5 - Production/Stable
Classifier: Intended Audience :: Developers
Classifier: License :: OSI Approved :: BSD License
Classifier: Natural Language :: English
Classifier: Programming Language :: Python
Classifier: Programming Language :: Python :: 3
Classifier: Topic :: Software Development :: Libraries :: Python Modules
License-File: LICENSE
Requires-Dist: setuptools
Requires-Dist: click >=8
Requires-Dist: click-plugins
